epyk_evergreen/PkgImports.py
epyk_evergreen/UI.py
epyk_evergreen/__init__.py
epyk_evergreen/_version.py
epyk_evergreen/html/HtmlEvrForms.py
epyk_evergreen/html/__init__.py
epyk_evergreen-0.0.1.dist-info/LICENSE
epyk_evergreen-0.0.1.dist-info/METADATA
epyk_evergreen-0.0.1.dist-info/WHEEL
epyk_evergreen-0.0.1.dist-info/top_level.txt
epyk_evergreen-0.0.1.dist-info/RECORD
